README.md
setup.py
cyolauthenticator/__init__.py
cyolauthenticator/chkpasswd.py
cyolauthenticator/chpasswd.py
cyolauthenticator/cyolauthenticator.py
cyolauthenticator/useradd.py
cyolauthenticator.egg-info/PKG-INFO
cyolauthenticator.egg-info/SOURCES.txt
cyolauthenticator.egg-info/dependency_links.txt
cyolauthenticator.egg-info/top_level.txt